sidefx_web/__init__.py
sidefx_web-0.6.0.dist-info/METADATA
sidefx_web-0.6.0.dist-info/RECORD
sidefx_web-0.6.0.dist-info/WHEEL
sidefx_web-0.6.0.dist-info/entry_points.txt
sidefx_web-0.6.0.dist-info/pbr.json
sidefx_web-0.6.0.dist-info/top_level.txt
