Metadata-Version: 2.1
Name: sidefx-web
Version: 0.6.0
Summary: Simple tool for using the SideFX Web API
Home-page: https://github.com/zxiiro/sidefx-web-cli
Author: Thanh Ha
Author-email: zxiiro@linux.com
License: MIT
Project-URL: Bug Tracker, https://github.com/zxiiro/sidefx-web-cli/issues
Project-URL: Source Code, https://github.com/zxiiro/sidefx-web-cli
Platform: UNKNOWN
Classifier: Intended Audience :: Developers
Classifier: Intended Audience :: Information Technology
Classifier: License :: OSI Approved :: MIT License
Classifier: Operating System :: POSIX :: Linux
Classifier: Programming Language :: Python
Classifier: Programming Language :: Python :: 3.5
Classifier: Programming Language :: Python :: 3.6
Classifier: Programming Language :: Python :: 3.7
Requires-Dist: requests (~=2.21.0)
